[
    {
        "name":"Sharath Sreekumar",
        "track":"Cloud"
    },
    {
        "name":"Shruti Chaturvedi",
        "track":"Cloud"
    },
    {
        "name":"SUTAPA DUTTA",
        "track":"Cloud"
    },
    {
        "name":"Valerian Pereira",
        "track":"Cloud"
    },
    {
        "name":"Akshay Desai",
        "track":"Cloud"
    },
    {
        "name":"Hrishabh Digaari",
        "track":"Cloud"
    },
    {
        "name":"Debal Bhattacharya",
        "track":"Cloud"
    },
    {
        "name":"Amol Borkar",
        "track":"Cloud"
    },
    {
        "name":"Heet Sheth",
        "track":"Cloud"
    },
    {
        "name":"Mangilipally Hari Prasad",
        "track":"Cloud"
    },
    {
        "name":"Aayush Srivastava",
        "track":"Cloud"
    },
    {
        "name":"Mayur Ganesh Narkhede",
        "track":"Cloud"
    },
    {
        "name":"Maneesh Manoj",
        "track":"Cloud"
    },
    {
        "name":"Subham Sahu",
        "track":"Cloud"
    },
    {
        "name":"Swastik Malakar",
        "track":"Cloud"
    },
    {
        "name":"Soham Malakar",
        "track":"Cloud"
    },
    {
        "name":"Kotharu Shanmukh Kiran",
        "track":"Cloud"
    },
    {
        "name":"Priyanka Garg",
        "track":"Cloud"
    },
    {
        "name":"Akshita Awasthi",
        "track":"Cloud"
    },
    {
        "name":"Debargha Mukherjee",
        "track":"Cloud"
    }
]